attributionpriors/__init__.py
attributionpriors/eager_ops.py
attributionpriors/ops.py
attributionpriors/mnist/__init__.py
attributionpriors/mnist/mnist_download.py
attributionpriors/mnist/mnist_model.py
attributionpriors/mnist/mnist_reader.py
attributionpriors/mnist/mnist_train.py
attributionpriors-0.1.3.dist-info/LICENSE
attributionpriors-0.1.3.dist-info/METADATA
attributionpriors-0.1.3.dist-info/WHEEL
attributionpriors-0.1.3.dist-info/top_level.txt
attributionpriors-0.1.3.dist-info/RECORD
