Metadata-Version: 2.1
Name: attributionpriors
Version: 0.1.3
Summary: Tools for training explainable models using attribution priors.
Home-page: https://github.com/suinleelab/attributionpriors
Author: The Lee Lab at UW
Author-email: psturm@cs.washington.edu
License: UNKNOWN
Platform: UNKNOWN
Classifier: Programming Language :: Python :: 3
Classifier: License :: OSI Approved :: MIT License
Classifier: Operating System :: OS Independent
Classifier: Intended Audience :: Science/Research
Classifier: Topic :: Scientific/Engineering
Requires-Dist: numpy
Requires-Dist: tensorflow
